twitter_cleanup/__init__.py
twitter_cleanup/__main__.py
twitter_cleanup/authentication.py
twitter_cleanup/botometer.py
twitter_cleanup/cache.py
twitter_cleanup/user.py
twitter_cleanup-0.0.6.dist-info/LICENSE
twitter_cleanup-0.0.6.dist-info/METADATA
twitter_cleanup-0.0.6.dist-info/WHEEL
twitter_cleanup-0.0.6.dist-info/entry_points.txt
twitter_cleanup-0.0.6.dist-info/top_level.txt
twitter_cleanup-0.0.6.dist-info/RECORD
