Metadata-Version: 2.1
Name: twitter-cleanup
Version: 0.0.6
Summary: Clean-up inactive accounts and bots from your Twitter
Home-page: https://github.com/cuducos/twitter-cleanup
Author: Eduardo Cuducos
License: GPLv3
Keywords: twitter,bots,social network
Platform: UNKNOWN
Classifier: Development Status :: 4 - Beta
Classifier: Intended Audience :: Developers
Classifier: Intended Audience :: End Users/Desktop
Classifier: License :: OSI Approved :: GNU General Public License v3 (GPLv3)
Classifier: Programming Language :: Python :: 3.6
Classifier: Programming Language :: Python :: 3.7
Classifier: Programming Language :: Python :: 3.8
Classifier: Topic :: Utilities
